klass/__init__.py
klass/classes/__init__.py
klass/classes/classification.py
klass/classes/codes.py
klass/classes/correspondence.py
klass/classes/family.py
klass/classes/search.py
klass/classes/variant.py
klass/classes/version.py
klass/config.py
klass/py.typed
klass/requests/__init__.py
klass/requests/klass_requests.py
klass/requests/klass_types.py
klass/requests/sections.py
klass/requests/validate.py
klass/utility/classification.py
klass/utility/cleanup.py
klass/utility/codes.py
klass/utility/naming.py
klass/widgets/__init__.py
klass/widgets/search_ipywidget.py
ssb_klass_python-1.0.5.dist-info/METADATA
ssb_klass_python-1.0.5.dist-info/WHEEL
ssb_klass_python-1.0.5.dist-info/licenses/LICENSE
ssb_klass_python-1.0.5.dist-info/RECORD
