Metadata-Version: 2.4
Name: ssb-klass-python
Version: 1.0.5
Summary: A Python package built on top of KLASS's API for retrieving classifications, codes, correspondences etc.
License-Expression: MIT
License-File: LICENSE
Author: Carl Corneil
Author-email: ssb-pythonistas <ssb-pythonistas@ssb.no>
Requires-Python: >=3.10,<4.0
Classifier: Development Status :: 4 - Beta
Classifier: Programming Language :: Python :: 3
Classifier: Programming Language :: Python :: 3.10
Classifier: Programming Language :: Python :: 3.11
Classifier: Programming Language :: Python :: 3.12
Classifier: Programming Language :: Python :: 3.13
Classifier: Programming Language :: Python :: 3.14
Requires-Dist: ipython (<9)
Requires-Dist: ipywidgets (>=8.0.6)
Requires-Dist: pandas (>=1.5.3)
Requires-Dist: python-dateutil (>=2.8.2)
Requires-Dist: requests (>=2.31.0)
Requires-Dist: toml (>=0.10.2)
Requires-Dist: typing-extensions (>=4.12.2)
Project-URL: Documentation, https://statisticsnorway.github.io/ssb-klass-python
Project-URL: Homepage, https://github.com/statisticsnorway/ssb-klass-python
Project-URL: Repository, https://github.com/statisticsnorway/ssb-klass-python
